pil_utils/__init__.py
pil_utils/build_image.py
pil_utils/gradient.py
pil_utils/text2image.py
pil_utils/typing.py
pil_utils/utils.py
pil_utils-0.2.2.dist-info/LICENSE
pil_utils-0.2.2.dist-info/METADATA
pil_utils-0.2.2.dist-info/WHEEL
pil_utils-0.2.2.dist-info/RECORD
