Metadata-Version: 2.1
Name: pil-utils
Version: 0.2.2
Summary: A simple PIL wrapper and text-to-image tool
Home-page: https://github.com/MeetWq/pil-utils
License: MIT
Author: meetwq
Author-email: meetwq@gmail.com
Requires-Python: >=3.9,<4.0
Classifier: License :: OSI Approved :: MIT License
Classifier: Programming Language :: Python :: 3
Classifier: Programming Language :: Python :: 3.9
Classifier: Programming Language :: Python :: 3.10
Classifier: Programming Language :: Python :: 3.11
Classifier: Programming Language :: Python :: 3.12
Classifier: Programming Language :: Python :: 3.13
Requires-Dist: Pillow (>=10.0.0,<12.0.0)
Requires-Dist: bbcode (>=1.1.0,<2.0.0)
Requires-Dist: msvc-runtime ; sys_platform == "win32"
Requires-Dist: numpy (>=1.21.0)
Requires-Dist: opencv-python-headless (>=4.0.0,<5.0.0)
Requires-Dist: skia-python (>=132.0b11)
Project-URL: Repository, https://github.com/MeetWq/pil-utils
